{
  "name": "db_rollback",
  "summary": "对于事务数据库，这将回滚最后一组操作。\n\n   回滚成功返回 1，失败返回 0 。",
  "details": "说明\nNot yet implemented!",
  "reference": [
    "db_commit",
    "db_exec",
    "valid_database"
  ],
  "category": "数据库相关函数（DB）",
  "signatures": [
    {
      "label": "int db_rollback( int handle )",
      "returnType": "int",
      "isVariadic": false,
      "parameters": [
        {
          "name": "handle",
          "type": "int"
        }
      ],
      "arity": {
        "min": 1,
        "max": 1
      }
    }
  ]
}
