{
  "name": "translate",
  "summary": "translate 内置函数",
  "category": "未归类函数",
  "signatures": [
    {
      "label": "float *translate(float *, float, float, float)",
      "returnType": "float *",
      "isVariadic": false,
      "parameters": [
        {
          "name": "arg1",
          "type": "float *"
        },
        {
          "name": "arg2",
          "type": "float"
        },
        {
          "name": "arg3",
          "type": "float"
        },
        {
          "name": "arg4",
          "type": "float"
        }
      ],
      "arity": {
        "min": 4,
        "max": 4
      }
    }
  ]
}
